MaNouvelleApp/__init__.py
MaNouvelleApp/admin.py
MaNouvelleApp/apps.py
MaNouvelleApp/models.py
MaNouvelleApp/tests.py
MaNouvelleApp/views.py
creator/__init__.py
creator/__main__.py
creator/create_app.py
creator/creator.py
django_app_creator_gbongue-0.1.dist-info/licenses/LICENSE
django_app_creator_gbongue-0.1.dist-info/METADATA
django_app_creator_gbongue-0.1.dist-info/WHEEL
django_app_creator_gbongue-0.1.dist-info/entry_points.txt
django_app_creator_gbongue-0.1.dist-info/top_level.txt
django_app_creator_gbongue-0.1.dist-info/RECORD
